<Properties StartupConfiguration="{565A1A93-1280-4003-BBD0-45F27919FA8F}|Default">
  <MonoDevelop.Ide.ItemProperties.Mediator PreferredExecutionTarget="/Applications/Google Chrome.app" />
  <MonoDevelop.Ide.Workbench ActiveDocument="Mediator/Application/UseCases/Customers/Command/Create/CreateCommand.cs">
    <Files>
      <File FileName="Mediator/Startup.cs" Line="38" Column="66" IsPinned="True" />
      <File FileName="Mediator/Presenter/Controller/CustomerController.cs" Line="29" Column="37" />
      <File FileName="Mediator/Application/UseCases/Customers/Command/Create/CreateCommand.cs" Line="9" Column="22" />
      <File FileName="Mediator/Application/UseCases/Customers/Command/Create/CreateCommandHandler.cs" Line="2" Column="53" />
      <File FileName="Mediator/Example.txt" Line="1" Column="1" />
    </Files>
    <Pads>
      <Pad Id="ProjectPad">
        <State name="__root__">
          <Node name="Mediator" expanded="True">
            <Node name="Mediator" expanded="True">
              <Node name="Application" expanded="True">
                <Node name="UseCases" expanded="True">
                  <Node name="Customers" expanded="True">
                    <Node name="Command" expanded="True">
                      <Node name="Create" expanded="True">
                        <Node name="CreateCommand.cs" selected="True" />
                      </Node>
                    </Node>
                    <Node name="Queries" expanded="True">
                      <Node name="Get" expanded="True" />
                      <Node name="GetbyId" expanded="True" />
                    </Node>
                  </Node>
                  <Node name="Orders" expanded="True">
                    <Node name="Command" expanded="True" />
                  </Node>
                </Node>
              </Node>
              <Node name="Presenter" expanded="True">
                <Node name="Controller" expanded="True" />
              </Node>
            </Node>
          </Node>
        </State>
      </Pad>
    </Pads>
  </MonoDevelop.Ide.Workbench>
  <MonoDevelop.Ide.DebuggingService.PinnedWatches />
  <MonoDevelop.Ide.Workspace ActiveConfiguration="Debug" />
  <MonoDevelop.Ide.DebuggingService.Breakpoints>
    <BreakpointStore />
  </MonoDevelop.Ide.DebuggingService.Breakpoints>
  <MultiItemStartupConfigurations />
</Properties>